async_promptic/__init__.py
async_promptic/django_support.py
async_promptic-5.5.12.dist-info/licenses/LICENSE
async_promptic-5.5.12.dist-info/WHEEL
async_promptic-5.5.12.dist-info/METADATA
async_promptic-5.5.12.dist-info/RECORD
