Metadata-Version: 2.4
Name: async-promptic
Version: 5.5.12
Summary: 90% of what you need for LLM app development. Nothing you don't.
Author-email: Pablo Schaffner <pablo@puntorigen.com>
Requires-Python: >=3.11
Classifier: License :: OSI Approved :: Apache Software License
Classifier: Programming Language :: Python :: 3
Classifier: Programming Language :: Python :: 3.11
Classifier: Programming Language :: Python :: 3.12
Classifier: Programming Language :: Python :: 3.13
License-File: LICENSE
Requires-Dist: jsonschema>=4.23.0
Requires-Dist: litellm~=1.38
Requires-Dist: pydantic~=2.7
Requires-Dist: fix-busted-json>=0.0.18
Requires-Dist: stamina>=25.1.0
Requires-Dist: json-repair>=0.40.0
Requires-Dist: fastmcp>=0.1.0
Project-URL: Home, https://github.com/puntorigen/async-promptic
